wrpc/__init__.py
wrpc/meta_pb2.py
wrpc/meta_pb2.pyi
wrpc/wrpc.py
websocket_rpcs-0.1.0.dist-info/METADATA
websocket_rpcs-0.1.0.dist-info/WHEEL
websocket_rpcs-0.1.0.dist-info/RECORD
