Metadata-Version: 2.1
Name: websocket-rpcs
Version: 0.1.0
Summary: rpc over websocket uses protobuf to serialize data
Author: jawide
Author-email: jawide@qq.com
Requires-Python: >=3.7,<4.0
Classifier: Programming Language :: Python :: 3
Classifier: Programming Language :: Python :: 3.7
Classifier: Programming Language :: Python :: 3.8
Classifier: Programming Language :: Python :: 3.9
Classifier: Programming Language :: Python :: 3.10
Classifier: Programming Language :: Python :: 3.11
Requires-Dist: protobuf (>=4.21.12,<5.0.0)
Requires-Dist: websockets (>=10.4,<11.0)
